{
  "created_at": "2026-02-18T15:07:15.323546",
  "max_dim": 2048,
  "total_source_bytes": 84704660,
  "total_output_bytes": 14320672,
  "total_bytes_saved": 70383988,
  "percent_smaller_overall": 0.8309340713958359,
  "images_converted": 67,
  "images_resized": 33,
  "rows": [
    {
      "relative_path": "3 PHase Service.jpeg",
      "source_ext": ".jpeg",
      "source_bytes": 75279,
      "output_bytes": 29906,
      "bytes_saved": 45373,
      "percent_smaller": 0.6027311733684029,
      "source_width": 480,
      "source_height": 640,
      "output_width": 480,
      "output_height": 640,
      "resized": false,
      "scale_long_edge": 1.0
    },
    {
      "relative_path": "7550693456474594645.jpg",
      "source_ext": ".jpg",
      "source_bytes": 640511,
      "output_bytes": 339712,
      "bytes_saved": 300799,
      "percent_smaller": 0.46962347250866887,
      "source_width": 2048,
      "source_height": 1536,
      "output_width": 2048,
      "output_height": 1536,
      "resized": false,
      "scale_long_edge": 1.0
    },
    {
      "relative_path": "After me.jpg",
      "source_ext": ".jpg",
      "source_bytes": 133636,
      "output_bytes": 77044,
      "bytes_saved": 56592,
      "percent_smaller": 0.4234787033434104,
      "source_width": 636,
      "source_height": 849,
      "output_width": 636,
      "output_height": 849,
      "resized": false,
      "scale_long_edge": 1.0
    },
    {
      "relative_path": "Air Compressor.jpeg",
      "source_ext": ".jpeg",
      "source_bytes": 2035546,
      "output_bytes": 176636,
      "bytes_saved": 1858910,
      "percent_smaller": 0.9132242651357425,
      "source_width": 3024,
      "source_height": 4032,
      "output_width": 1536,
      "output_height": 2048,
      "resized": true,
      "scale_long_edge": 0.5079365079365079
    },
    {
      "relative_path": "Barn.jpeg",
      "source_ext": ".jpeg",
      "source_bytes": 2436383,
      "output_bytes": 331814,
      "bytes_saved": 2104569,
      "percent_smaller": 0.863808768982545,
      "source_width": 3024,
      "source_height": 4032,
      "output_width": 1536,
      "output_height": 2048,
      "resized": true,
      "scale_long_edge": 0.5079365079365079
    },
    {
      "relative_path": "Before me.jpg",
      "source_ext": ".jpg",
      "source_bytes": 21648,
      "output_bytes": 11540,
      "bytes_saved": 10108,
      "percent_smaller": 0.46692535107169253,
      "source_width": 204,
      "source_height": 272,
      "output_width": 204,
      "output_height": 272,
      "resized": false,
      "scale_long_edge": 1.0
    },
    {
      "relative_path": "Blower Motor.jpeg",
      "source_ext": ".jpeg",
      "source_bytes": 3688876,
      "output_bytes": 732406,
      "bytes_saved": 2956470,
      "percent_smaller": 0.8014555111096171,
      "source_width": 4032,
      "source_height": 3024,
      "output_width": 2048,
      "output_height": 1536,
      "resized": true,
      "scale_long_edge": 0.5079365079365079
    },
    {
      "relative_path": "CT CABINET Service upgrade.jpg",
      "source_ext": ".jpg",
      "source_bytes": 24770,
      "output_bytes": 12978,
      "bytes_saved": 11792,
      "percent_smaller": 0.4760597496972143,
      "source_width": 214,
      "source_height": 286,
      "output_width": 214,
      "output_height": 286,
      "resized": false,
      "scale_long_edge": 1.0
    },
    {
      "relative_path": "Conduit Piping.jpg",
      "source_ext": ".jpg",
      "source_bytes": 209506,
      "output_bytes": 94212,
      "bytes_saved": 115294,
      "percent_smaller": 0.5503135948373794,
      "source_width": 1200,
      "source_height": 1600,
      "output_width": 1200,
      "output_height": 1600,
      "resized": false,
      "scale_long_edge": 1.0
    },
    {
      "relative_path": "Conduit.jpg",
      "source_ext": ".jpg",
      "source_bytes": 260781,
      "output_bytes": 131356,
      "bytes_saved": 129425,
      "percent_smaller": 0.49629765972214235,
      "source_width": 1200,
      "source_height": 1600,
      "output_width": 1200,
      "output_height": 1600,
      "resized": false,
      "scale_long_edge": 1.0
    },
    {
      "relative_path": "Control Cabinet.jpeg",
      "source_ext": ".jpeg",
      "source_bytes": 2750699,
      "output_bytes": 430296,
      "bytes_saved": 2320403,
      "percent_smaller": 0.8435684893185332,
      "source_width": 3024,
      "source_height": 4032,
      "output_width": 1536,
      "output_height": 2048,
      "resized": true,
      "scale_long_edge": 0.5079365079365079
    },
    {
      "relative_path": "Control Work.jpeg",
      "source_ext": ".jpeg",
      "source_bytes": 107813,
      "output_bytes": 53036,
      "bytes_saved": 54777,
      "percent_smaller": 0.5080741654531458,
      "source_width": 480,
      "source_height": 640,
      "output_width": 480,
      "output_height": 640,
      "resized": false,
      "scale_long_edge": 1.0
    },
    {
      "relative_path": "Counter Bar Lighting.jpg",
      "source_ext": ".jpg",
      "source_bytes": 226590,
      "output_bytes": 90702,
      "bytes_saved": 135888,
      "percent_smaller": 0.5997087250099298,
      "source_width": 1392,
      "source_height": 857,
      "output_width": 1392,
      "output_height": 857,
      "resized": false,
      "scale_long_edge": 1.0
    },
    {
      "relative_path": "Dust Collector System.jpg",
      "source_ext": ".jpg",
      "source_bytes": 307886,
      "output_bytes": 178458,
      "bytes_saved": 129428,
      "percent_smaller": 0.42037637307315046,
      "source_width": 1200,
      "source_height": 1600,
      "output_width": 1200,
      "output_height": 1600,
      "resized": false,
      "scale_long_edge": 1.0
    },
    {
      "relative_path": "Dust Collector motor.jpg",
      "source_ext": ".jpg",
      "source_bytes": 223998,
      "output_bytes": 150354,
      "bytes_saved": 73644,
      "percent_smaller": 0.32877079259636244,
      "source_width": 1200,
      "source_height": 900,
      "output_width": 1200,
      "output_height": 900,
      "resized": false,
      "scale_long_edge": 1.0
    },
    {
      "relative_path": "EMT Piping.jpeg",
      "source_ext": ".jpeg",
      "source_bytes": 2750935,
      "output_bytes": 481426,
      "bytes_saved": 2269509,
      "percent_smaller": 0.82499550152948,
      "source_width": 3024,
      "source_height": 4032,
      "output_width": 1536,
      "output_height": 2048,
      "resized": true,
      "scale_long_edge": 0.5079365079365079
    },
    {
      "relative_path": "Electrical Panels.jpg",
      "source_ext": ".jpg",
      "source_bytes": 180700,
      "output_bytes": 113858,
      "bytes_saved": 66842,
      "percent_smaller": 0.36990592141671275,
      "source_width": 686,
      "source_height": 915,
      "output_width": 686,
      "output_height": 915,
      "resized": false,
      "scale_long_edge": 1.0
    },
    {
      "relative_path": "Exterior Light Fixtures.jpeg",
      "source_ext": ".jpeg",
      "source_bytes": 2369583,
      "output_bytes": 325554,
      "bytes_saved": 2044029,
      "percent_smaller": 0.8626112695778118,
      "source_width": 4032,
      "source_height": 3024,
      "output_width": 2048,
      "output_height": 1536,
      "resized": true,
      "scale_long_edge": 0.5079365079365079
    },
    {
      "relative_path": "Field Controls.jpeg",
      "source_ext": ".jpeg",
      "source_bytes": 2232581,
      "output_bytes": 294728,
      "bytes_saved": 1937853,
      "percent_smaller": 0.8679877684169129,
      "source_width": 3024,
      "source_height": 4032,
      "output_width": 1536,
      "output_height": 2048,
      "resized": true,
      "scale_long_edge": 0.5079365079365079
    },
    {
      "relative_path": "Fire Response.jpg",
      "source_ext": ".jpg",
      "source_bytes": 341902,
      "output_bytes": 191542,
      "bytes_saved": 150360,
      "percent_smaller": 0.4397751402448655,
      "source_width": 1200,
      "source_height": 1600,
      "output_width": 1200,
      "output_height": 1600,
      "resized": false,
      "scale_long_edge": 1.0
    },
    {
      "relative_path": "Gas Station Service Call .jpeg",
      "source_ext": ".jpeg",
      "source_bytes": 4674447,
      "output_bytes": 410022,
      "bytes_saved": 4264425,
      "percent_smaller": 0.9122843835859087,
      "source_width": 5712,
      "source_height": 4284,
      "output_width": 2048,
      "output_height": 1536,
      "resized": true,
      "scale_long_edge": 0.3585434173669468
    },
    {
      "relative_path": "Horse Barn.jpg",
      "source_ext": ".jpg",
      "source_bytes": 1857099,
      "output_bytes": 392840,
      "bytes_saved": 1464259,
      "percent_smaller": 0.7884657737686575,
      "source_width": 3024,
      "source_height": 4032,
      "output_width": 1536,
      "output_height": 2048,
      "resized": true,
      "scale_long_edge": 0.5079365079365079
    },
    {
      "relative_path": "Horse Stall Lighting.jpeg",
      "source_ext": ".jpeg",
      "source_bytes": 2417036,
      "output_bytes": 326750,
      "bytes_saved": 2090286,
      "percent_smaller": 0.8648137636344679,
      "source_width": 4032,
      "source_height": 3024,
      "output_width": 2048,
      "output_height": 1536,
      "resized": true,
      "scale_long_edge": 0.5079365079365079
    },
    {
      "relative_path": "IMG_0733.jpg",
      "source_ext": ".jpg",
      "source_bytes": 52428,
      "output_bytes": 26700,
      "bytes_saved": 25728,
      "percent_smaller": 0.49073014419775696,
      "source_width": 438,
      "source_height": 328,
      "output_width": 438,
      "output_height": 328,
      "resized": false,
      "scale_long_edge": 1.0
    },
    {
      "relative_path": "IMG_0852.jpg",
      "source_ext": ".jpg",
      "source_bytes": 33016,
      "output_bytes": 13496,
      "bytes_saved": 19520,
      "percent_smaller": 0.5912284952750182,
      "source_width": 438,
      "source_height": 328,
      "output_width": 438,
      "output_height": 328,
      "resized": false,
      "scale_long_edge": 1.0
    },
    {
      "relative_path": "IMG_1380.HEIC",
      "source_ext": ".heic",
      "source_bytes": 1698961,
      "output_bytes": 305700,
      "bytes_saved": 1393261,
      "percent_smaller": 0.8200664994664386,
      "source_width": 4032,
      "source_height": 3024,
      "output_width": 2048,
      "output_height": 1536,
      "resized": true,
      "scale_long_edge": 0.5079365079365079
    },
    {
      "relative_path": "IMG_1599_Original.PNG",
      "source_ext": ".png",
      "source_bytes": 3662360,
      "output_bytes": 684932,
      "bytes_saved": 2977428,
      "percent_smaller": 0.8129807009687742,
      "source_width": 828,
      "source_height": 1792,
      "output_width": 828,
      "output_height": 1792,
      "resized": false,
      "scale_long_edge": 1.0
    },
    {
      "relative_path": "IMG_8814.HEIC",
      "source_ext": ".heic",
      "source_bytes": 1750180,
      "output_bytes": 301786,
      "bytes_saved": 1448394,
      "percent_smaller": 0.8275685929447256,
      "source_width": 4032,
      "source_height": 3024,
      "output_width": 2048,
      "output_height": 1536,
      "resized": true,
      "scale_long_edge": 0.5079365079365079
    },
    {
      "relative_path": "Interior LED lighitng.jpeg",
      "source_ext": ".jpeg",
      "source_bytes": 2336984,
      "output_bytes": 269720,
      "bytes_saved": 2067264,
      "percent_smaller": 0.8845862872830965,
      "source_width": 4032,
      "source_height": 3024,
      "output_width": 2048,
      "output_height": 1536,
      "resized": true,
      "scale_long_edge": 0.5079365079365079
    },
    {
      "relative_path": "LED Hand Rail.jpeg",
      "source_ext": ".jpeg",
      "source_bytes": 1427891,
      "output_bytes": 96392,
      "bytes_saved": 1331499,
      "percent_smaller": 0.9324934466286292,
      "source_width": 4032,
      "source_height": 3024,
      "output_width": 2048,
      "output_height": 1536,
      "resized": true,
      "scale_long_edge": 0.5079365079365079
    },
    {
      "relative_path": "LED HandRail.jpeg",
      "source_ext": ".jpeg",
      "source_bytes": 1827671,
      "output_bytes": 121462,
      "bytes_saved": 1706209,
      "percent_smaller": 0.9335427437432667,
      "source_width": 3024,
      "source_height": 4032,
      "output_width": 1536,
      "output_height": 2048,
      "resized": true,
      "scale_long_edge": 0.5079365079365079
    },
    {
      "relative_path": "LED shelves.jpeg",
      "source_ext": ".jpeg",
      "source_bytes": 78944,
      "output_bytes": 34908,
      "bytes_saved": 44036,
      "percent_smaller": 0.5578131333603566,
      "source_width": 640,
      "source_height": 480,
      "output_width": 640,
      "output_height": 480,
      "resized": false,
      "scale_long_edge": 1.0
    },
    {
      "relative_path": "LOGO.jpeg",
      "source_ext": ".jpeg",
      "source_bytes": 83293,
      "output_bytes": 31640,
      "bytes_saved": 51653,
      "percent_smaller": 0.620136145894613,
      "source_width": 640,
      "source_height": 640,
      "output_width": 640,
      "output_height": 640,
      "resized": false,
      "scale_long_edge": 1.0
    },
    {
      "relative_path": "Light Fixture.jpeg",
      "source_ext": ".jpeg",
      "source_bytes": 2161457,
      "output_bytes": 287372,
      "bytes_saved": 1874085,
      "percent_smaller": 0.8670470890700116,
      "source_width": 3024,
      "source_height": 4032,
      "output_width": 1536,
      "output_height": 2048,
      "resized": true,
      "scale_long_edge": 0.5079365079365079
    },
    {
      "relative_path": "Lighting Fixture.HEIC",
      "source_ext": ".heic",
      "source_bytes": 2684579,
      "output_bytes": 458306,
      "bytes_saved": 2226273,
      "percent_smaller": 0.8292819842515344,
      "source_width": 4032,
      "source_height": 3024,
      "output_width": 2048,
      "output_height": 1536,
      "resized": true,
      "scale_long_edge": 0.5079365079365079
    },
    {
      "relative_path": "Lighting.jpg",
      "source_ext": ".jpg",
      "source_bytes": 179425,
      "output_bytes": 102092,
      "bytes_saved": 77333,
      "percent_smaller": 0.4310045980214574,
      "source_width": 1200,
      "source_height": 900,
      "output_width": 1200,
      "output_height": 900,
      "resized": false,
      "scale_long_edge": 1.0
    },
    {
      "relative_path": "Low Voltage LED.jpeg",
      "source_ext": ".jpeg",
      "source_bytes": 1468371,
      "output_bytes": 79366,
      "bytes_saved": 1389005,
      "percent_smaller": 0.9459496271718796,
      "source_width": 3024,
      "source_height": 4032,
      "output_width": 1536,
      "output_height": 2048,
      "resized": true,
      "scale_long_edge": 0.5079365079365079
    },
    {
      "relative_path": "Meter Socket Bank.jpeg",
      "source_ext": ".jpeg",
      "source_bytes": 2236138,
      "output_bytes": 252690,
      "bytes_saved": 1983448,
      "percent_smaller": 0.8869971352394173,
      "source_width": 3024,
      "source_height": 4032,
      "output_width": 1536,
      "output_height": 2048,
      "resized": true,
      "scale_long_edge": 0.5079365079365079
    },
    {
      "relative_path": "Motor Control.jpeg",
      "source_ext": ".jpeg",
      "source_bytes": 2428905,
      "output_bytes": 332036,
      "bytes_saved": 2096869,
      "percent_smaller": 0.8632980705297243,
      "source_width": 3024,
      "source_height": 4032,
      "output_width": 1536,
      "output_height": 2048,
      "resized": true,
      "scale_long_edge": 0.5079365079365079
    },
    {
      "relative_path": "Motor.jpeg",
      "source_ext": ".jpeg",
      "source_bytes": 66308,
      "output_bytes": 26692,
      "bytes_saved": 39616,
      "percent_smaller": 0.5974543041563612,
      "source_width": 480,
      "source_height": 640,
      "output_width": 480,
      "output_height": 640,
      "resized": false,
      "scale_long_edge": 1.0
    },
    {
      "relative_path": "Multi panel Assembly.HEIC",
      "source_ext": ".heic",
      "source_bytes": 1600981,
      "output_bytes": 230060,
      "bytes_saved": 1370921,
      "percent_smaller": 0.8563006056911356,
      "source_width": 4032,
      "source_height": 3024,
      "output_width": 2048,
      "output_height": 1536,
      "resized": true,
      "scale_long_edge": 0.5079365079365079
    },
    {
      "relative_path": "Panel Work.jpeg",
      "source_ext": ".jpeg",
      "source_bytes": 2699241,
      "output_bytes": 358468,
      "bytes_saved": 2340773,
      "percent_smaller": 0.8671967416025468,
      "source_width": 3024,
      "source_height": 4032,
      "output_width": 1536,
      "output_height": 2048,
      "resized": true,
      "scale_long_edge": 0.5079365079365079
    },
    {
      "relative_path": "Piping (2).jpg",
      "source_ext": ".jpg",
      "source_bytes": 151977,
      "output_bytes": 86398,
      "bytes_saved": 65579,
      "percent_smaller": 0.43150608315731986,
      "source_width": 686,
      "source_height": 915,
      "output_width": 686,
      "output_height": 915,
      "resized": false,
      "scale_long_edge": 1.0
    },
    {
      "relative_path": "Piping.jpg",
      "source_ext": ".jpg",
      "source_bytes": 191899,
      "output_bytes": 87322,
      "bytes_saved": 104577,
      "percent_smaller": 0.5449585459017504,
      "source_width": 1200,
      "source_height": 1600,
      "output_width": 1200,
      "output_height": 1600,
      "resized": false,
      "scale_long_edge": 1.0
    },
    {
      "relative_path": "Residential Electrical.jpeg",
      "source_ext": ".jpeg",
      "source_bytes": 1913232,
      "output_bytes": 189902,
      "bytes_saved": 1723330,
      "percent_smaller": 0.9007428267977956,
      "source_width": 3024,
      "source_height": 4032,
      "output_width": 1536,
      "output_height": 2048,
      "resized": true,
      "scale_long_edge": 0.5079365079365079
    },
    {
      "relative_path": "Residential Panel.jpeg",
      "source_ext": ".jpeg",
      "source_bytes": 2723664,
      "output_bytes": 336318,
      "bytes_saved": 2387346,
      "percent_smaller": 0.8765200112789243,
      "source_width": 3024,
      "source_height": 4032,
      "output_width": 1536,
      "output_height": 2048,
      "resized": true,
      "scale_long_edge": 0.5079365079365079
    },
    {
      "relative_path": "Residential Wiring.HEIC",
      "source_ext": ".heic",
      "source_bytes": 952714,
      "output_bytes": 303390,
      "bytes_saved": 649324,
      "percent_smaller": 0.6815518613140985,
      "source_width": 4032,
      "source_height": 3024,
      "output_width": 2048,
      "output_height": 1536,
      "resized": true,
      "scale_long_edge": 0.5079365079365079
    },
    {
      "relative_path": "Residential panel  work.jpg",
      "source_ext": ".jpg",
      "source_bytes": 170239,
      "output_bytes": 102220,
      "bytes_saved": 68019,
      "percent_smaller": 0.39955004434941466,
      "source_width": 636,
      "source_height": 849,
      "output_width": 636,
      "output_height": 849,
      "resized": false,
      "scale_long_edge": 1.0
    },
    {
      "relative_path": "Selenoids.jpg",
      "source_ext": ".jpg",
      "source_bytes": 229260,
      "output_bytes": 109224,
      "bytes_saved": 120036,
      "percent_smaller": 0.5235802146035069,
      "source_width": 1200,
      "source_height": 1600,
      "output_width": 1200,
      "output_height": 1600,
      "resized": false,
      "scale_long_edge": 1.0
    },
    {
      "relative_path": "Service after.jpeg",
      "source_ext": ".jpeg",
      "source_bytes": 2369600,
      "output_bytes": 318458,
      "bytes_saved": 2051142,
      "percent_smaller": 0.8656068534773802,
      "source_width": 3024,
      "source_height": 4032,
      "output_width": 1536,
      "output_height": 2048,
      "resized": true,
      "scale_long_edge": 0.5079365079365079
    },
    {
      "relative_path": "Service before.jpeg",
      "source_ext": ".jpeg",
      "source_bytes": 2551071,
      "output_bytes": 292962,
      "bytes_saved": 2258109,
      "percent_smaller": 0.8851611734836075,
      "source_width": 3024,
      "source_height": 4032,
      "output_width": 1536,
      "output_height": 2048,
      "resized": true,
      "scale_long_edge": 0.5079365079365079
    },
    {
      "relative_path": "SteelTech Conduit Room.jpeg",
      "source_ext": ".jpeg",
      "source_bytes": 2766137,
      "output_bytes": 386824,
      "bytes_saved": 2379313,
      "percent_smaller": 0.8601573240949382,
      "source_width": 3024,
      "source_height": 4032,
      "output_width": 1536,
      "output_height": 2048,
      "resized": true,
      "scale_long_edge": 0.5079365079365079
    },
    {
      "relative_path": "Switch Gear.jpg",
      "source_ext": ".jpg",
      "source_bytes": 13244,
      "output_bytes": 6904,
      "bytes_saved": 6340,
      "percent_smaller": 0.47870733917245545,
      "source_width": 165,
      "source_height": 220,
      "output_width": 165,
      "output_height": 220,
      "resized": false,
      "scale_long_edge": 1.0
    },
    {
      "relative_path": "TopTierElectrical_Logo_Web_600w.webp",
      "source_ext": ".webp",
      "source_bytes": 341354,
      "output_bytes": 341354,
      "bytes_saved": 0,
      "percent_smaller": 0.0,
      "source_width": 600,
      "source_height": 574,
      "output_width": 600,
      "output_height": 574,
      "resized": false,
      "scale_long_edge": 1.0
    },
    {
      "relative_path": "TopTierElectrical_OpenGraph_1200x630.png",
      "source_ext": ".png",
      "source_bytes": 337224,
      "output_bytes": 237646,
      "bytes_saved": 99578,
      "percent_smaller": 0.2952874054041231,
      "source_width": 1200,
      "source_height": 630,
      "output_width": 1200,
      "output_height": 630,
      "resized": false,
      "scale_long_edge": 1.0
    },
    {
      "relative_path": "Transformer.HEIC",
      "source_ext": ".heic",
      "source_bytes": 1938535,
      "output_bytes": 396132,
      "bytes_saved": 1542403,
      "percent_smaller": 0.7956539345433536,
      "source_width": 4032,
      "source_height": 3024,
      "output_width": 2048,
      "output_height": 1536,
      "resized": true,
      "scale_long_edge": 0.5079365079365079
    },
    {
      "relative_path": "What not to do/Electrical Fail.HEIC",
      "source_ext": ".heic",
      "source_bytes": 1508859,
      "output_bytes": 275694,
      "bytes_saved": 1233165,
      "percent_smaller": 0.8172831258586787,
      "source_width": 4032,
      "source_height": 3024,
      "output_width": 2048,
      "output_height": 1536,
      "resized": true,
      "scale_long_edge": 0.5079365079365079
    },
    {
      "relative_path": "What not to do/Electrical Mess.HEIC",
      "source_ext": ".heic",
      "source_bytes": 2492718,
      "output_bytes": 591218,
      "bytes_saved": 1901500,
      "percent_smaller": 0.7628219477694629,
      "source_width": 4032,
      "source_height": 3024,
      "output_width": 2048,
      "output_height": 1536,
      "resized": true,
      "scale_long_edge": 0.5079365079365079
    },
    {
      "relative_path": "What not to do/IMG_0099.jpg",
      "source_ext": ".jpg",
      "source_bytes": 24497,
      "output_bytes": 12650,
      "bytes_saved": 11847,
      "percent_smaller": 0.48361023798832514,
      "source_width": 293,
      "source_height": 220,
      "output_width": 293,
      "output_height": 220,
      "resized": false,
      "scale_long_edge": 1.0
    },
    {
      "relative_path": "What not to do/IMG_2522.jpg",
      "source_ext": ".jpg",
      "source_bytes": 27249,
      "output_bytes": 13650,
      "bytes_saved": 13599,
      "percent_smaller": 0.4990641858416822,
      "source_width": 274,
      "source_height": 206,
      "output_width": 274,
      "output_height": 206,
      "resized": false,
      "scale_long_edge": 1.0
    },
    {
      "relative_path": "What not to do/IMG_3108.jpg",
      "source_ext": ".jpg",
      "source_bytes": 16739,
      "output_bytes": 9228,
      "bytes_saved": 7511,
      "percent_smaller": 0.44871258737081066,
      "source_width": 165,
      "source_height": 220,
      "output_width": 165,
      "output_height": 220,
      "resized": false,
      "scale_long_edge": 1.0
    },
    {
      "relative_path": "What not to do/IMG_6894.jpg",
      "source_ext": ".jpg",
      "source_bytes": 19717,
      "output_bytes": 9994,
      "bytes_saved": 9723,
      "percent_smaller": 0.49312775777248063,
      "source_width": 187,
      "source_height": 249,
      "output_width": 187,
      "output_height": 249,
      "resized": false,
      "scale_long_edge": 1.0
    },
    {
      "relative_path": "What not to do/IMG_8175.jpg",
      "source_ext": ".jpg",
      "source_bytes": 16949,
      "output_bytes": 9208,
      "bytes_saved": 7741,
      "percent_smaller": 0.4567231105079945,
      "source_width": 138,
      "source_height": 184,
      "output_width": 138,
      "output_height": 184,
      "resized": false,
      "scale_long_edge": 1.0
    },
    {
      "relative_path": "Working through the Storms.jpg",
      "source_ext": ".jpg",
      "source_bytes": 217387,
      "output_bytes": 103702,
      "bytes_saved": 113685,
      "percent_smaller": 0.5229613546348217,
      "source_width": 1500,
      "source_height": 2000,
      "output_width": 1500,
      "output_height": 2000,
      "resized": false,
      "scale_long_edge": 1.0
    },
    {
      "relative_path": "backup Generator.HEIC",
      "source_ext": ".heic",
      "source_bytes": 2003505,
      "output_bytes": 276820,
      "bytes_saved": 1726685,
      "percent_smaller": 0.8618321391760939,
      "source_width": 4032,
      "source_height": 3024,
      "output_width": 2048,
      "output_height": 1536,
      "resized": true,
      "scale_long_edge": 0.5079365079365079
    },
    {
      "relative_path": "on site Service Sketch.heic",
      "source_ext": ".heic",
      "source_bytes": 3138479,
      "output_bytes": 351418,
      "bytes_saved": 2787061,
      "percent_smaller": 0.8880292014061588,
      "source_width": 4032,
      "source_height": 3024,
      "output_width": 2048,
      "output_height": 1536,
      "resized": true,
      "scale_long_edge": 0.5079365079365079
    },
    {
      "relative_path": "panel.jpg",
      "source_ext": ".jpg",
      "source_bytes": 143073,
      "output_bytes": 81048,
      "bytes_saved": 62025,
      "percent_smaller": 0.43351995135350485,
      "source_width": 686,
      "source_height": 915,
      "output_width": 686,
      "output_height": 915,
      "resized": false,
      "scale_long_edge": 1.0
    }
  ]
}